scribemi/ScribeMi.py
scribemi/__init__.py
scribemi-1.2.0.dist-info/LICENSE.md
scribemi-1.2.0.dist-info/METADATA
scribemi-1.2.0.dist-info/WHEEL
scribemi-1.2.0.dist-info/top_level.txt
scribemi-1.2.0.dist-info/RECORD
